payfast_client/__init__.py
payfast_client/client.py
payfast_client/py.typed
payfast_client-0.1.3.dist-info/LICENSE
payfast_client-0.1.3.dist-info/WHEEL
payfast_client-0.1.3.dist-info/METADATA
payfast_client-0.1.3.dist-info/RECORD
